line_protocol_parser/__init__.py
line_protocol_parser/_line_protocol_parser.cpython-314-x86_64-linux-gnu.so
line_protocol_parser-1.1.3.dist-info/METADATA
line_protocol_parser-1.1.3.dist-info/WHEEL
line_protocol_parser-1.1.3.dist-info/top_level.txt
line_protocol_parser-1.1.3.dist-info/RECORD
line_protocol_parser-1.1.3.dist-info/licenses/LICENSE.md
